{"nodes": [{"id": "home_max_development_hero_tests_test_locks_py", "label": "test_locks.py", "file_type": "code", "source_file": "tests/test_locks.py", "source_location": "L1"}, {"id": "tests_test_locks_isolate_lock_dir", "label": "_isolate_lock_dir()", "file_type": "code", "source_file": "tests/test_locks.py", "source_location": "L20"}, {"id": "monkeypatch", "label": "MonkeyPatch", "file_type": "code", "source_file": "tests/test_locks.py", "source_location": "L20"}, {"id": "path", "label": "Path", "file_type": "code", "source_file": "tests/test_locks.py", "source_location": "L20"}, {"id": "tests_test_locks_testfilelock", "label": "TestFileLock", "file_type": "code", "source_file": "tests/test_locks.py", "source_location": "L29"}, {"id": "tests_test_locks_testfilelock_test_acquire_and_release", "label": ".test_acquire_and_release()", "file_type": "code", "source_file": "tests/test_locks.py", "source_location": "L32"}, {"id": "tests_test_locks_testfilelock_test_lock_path_created", "label": ".test_lock_path_created()", "file_type": "code", "source_file": "tests/test_locks.py", "source_location": "L47"}, {"id": "tests_test_locks_testfilelock_test_different_resources_dont_block", "label": ".test_different_resources_dont_block()", "file_type": "code", "source_file": "tests/test_locks.py", "source_location": "L55"}, {"id": "tests_test_locks_testfilelock_test_timeout_when_contended", "label": ".test_timeout_when_contended()", "file_type": "code", "source_file": "tests/test_locks.py", "source_location": "L66"}, {"id": "tests_test_locks_testfilelock_test_reentrant_same_process", "label": ".test_reentrant_same_process()", "file_type": "code", "source_file": "tests/test_locks.py", "source_location": "L98"}, {"id": "tests_test_locks_testfilelock_test_lock_exclusive_across_threads", "label": ".test_lock_exclusive_across_threads()", "file_type": "code", "source_file": "tests/test_locks.py", "source_location": "L108"}, {"id": "tests_test_locks_testfilelock_test_cleanup_on_file_not_exists", "label": ".test_cleanup_on_file_not_exists()", "file_type": "code", "source_file": "tests/test_locks.py", "source_location": "L143"}, {"id": "tests_test_locks_testfilelock_test_default_timeout", "label": ".test_default_timeout()", "file_type": "code", "source_file": "tests/test_locks.py", "source_location": "L159"}, {"id": "tests_test_locks_testfilelock_test_custom_timeout_and_poll", "label": ".test_custom_timeout_and_poll()", "file_type": "code", "source_file": "tests/test_locks.py", "source_location": "L165"}, {"id": "tests_test_locks_testexchange", "label": "TestExchange", "file_type": "code", "source_file": "tests/test_locks.py", "source_location": "L174"}, {"id": "tests_test_locks_testexchange_isolate_exchange_dir", "label": "._isolate_exchange_dir()", "file_type": "code", "source_file": "tests/test_locks.py", "source_location": "L178"}, {"id": "tests_test_locks_testexchange_test_post_and_read_messages", "label": ".test_post_and_read_messages()", "file_type": "code", "source_file": "tests/test_locks.py", "source_location": "L187"}, {"id": "tests_test_locks_testexchange_test_post_message_returns_path", "label": ".test_post_message_returns_path()", "file_type": "code", "source_file": "tests/test_locks.py", "source_location": "L202"}, {"id": "tests_test_locks_testexchange_test_read_empty_channel", "label": ".test_read_empty_channel()", "file_type": "code", "source_file": "tests/test_locks.py", "source_location": "L215"}, {"id": "tests_test_locks_testexchange_test_read_empty_messages_dir", "label": ".test_read_empty_messages_dir()", "file_type": "code", "source_file": "tests/test_locks.py", "source_location": "L222"}, {"id": "tests_test_locks_testexchange_test_read_state", "label": ".test_read_state()", "file_type": "code", "source_file": "tests/test_locks.py", "source_location": "L230"}, {"id": "tests_test_locks_testexchange_test_write_state_overwrites", "label": ".test_write_state_overwrites()", "file_type": "code", "source_file": "tests/test_locks.py", "source_location": "L243"}, {"id": "tests_test_locks_testexchange_test_ensure_channel", "label": ".test_ensure_channel()", "file_type": "code", "source_file": "tests/test_locks.py", "source_location": "L255"}, {"id": "tests_test_locks_testexchange_test_post_message_sequence_ordering", "label": ".test_post_message_sequence_ordering()", "file_type": "code", "source_file": "tests/test_locks.py", "source_location": "L264"}, {"id": "tests_test_locks_testexchange_test_message_round_trip", "label": ".test_message_round_trip()", "file_type": "code", "source_file": "tests/test_locks.py", "source_location": "L278"}, {"id": "tests_test_locks_testlockandexchange", "label": "TestLockAndExchange", "file_type": "code", "source_file": "tests/test_locks.py", "source_location": "L297"}, {"id": "tests_test_locks_testlockandexchange_isolate", "label": "._isolate()", "file_type": "code", "source_file": "tests/test_locks.py", "source_location": "L301"}, {"id": "tests_test_locks_testlockandexchange_test_write_state_under_lock", "label": ".test_write_state_under_lock()", "file_type": "code", "source_file": "tests/test_locks.py", "source_location": "L312"}, {"id": "tests_test_locks_testlockandexchange_test_same_channel_multiple_soldiers", "label": ".test_same_channel_multiple_soldiers()", "file_type": "code", "source_file": "tests/test_locks.py", "source_location": "L328"}, {"id": "tests_test_locks_rationale_1", "label": "Tests for hero.core.locks (FileLock) and hero.core.exchange.", "file_type": "rationale", "source_file": "tests/test_locks.py", "source_location": "L1"}, {"id": "tests_test_locks_rationale_21", "label": "Redirect LOCK_DIR to a temp directory so tests are isolated.", "file_type": "rationale", "source_file": "tests/test_locks.py", "source_location": "L21"}, {"id": "tests_test_locks_rationale_30", "label": "Tests for hero.core.locks.FileLock.", "file_type": "rationale", "source_file": "tests/test_locks.py", "source_location": "L30"}, {"id": "tests_test_locks_rationale_33", "label": "FileLock is acquired and released correctly.", "file_type": "rationale", "source_file": "tests/test_locks.py", "source_location": "L33"}, {"id": "tests_test_locks_rationale_48", "label": "Lock file is created in the correct directory.", "file_type": "rationale", "source_file": "tests/test_locks.py", "source_location": "L48"}, {"id": "tests_test_locks_rationale_56", "label": "Two locks on different resource names can be held simultaneously.", "file_type": "rationale", "source_file": "tests/test_locks.py", "source_location": "L56"}, {"id": "tests_test_locks_rationale_67", "label": "FileLock raises TimeoutError when another process holds the lock.          Uses", "file_type": "rationale", "source_file": "tests/test_locks.py", "source_location": "L67"}, {"id": "tests_test_locks_rationale_99", "label": "Within the same process, FileLock can be acquired again after release.", "file_type": "rationale", "source_file": "tests/test_locks.py", "source_location": "L99"}, {"id": "tests_test_locks_rationale_109", "label": "Two threads in the same process both wait but only one holds at a time.", "file_type": "rationale", "source_file": "tests/test_locks.py", "source_location": "L109"}, {"id": "tests_test_locks_rationale_144", "label": "Even if the lock file is removed while held, __exit__ is safe.", "file_type": "rationale", "source_file": "tests/test_locks.py", "source_location": "L144"}, {"id": "tests_test_locks_rationale_160", "label": "Default timeout is 30.0 seconds.", "file_type": "rationale", "source_file": "tests/test_locks.py", "source_location": "L160"}, {"id": "tests_test_locks_rationale_166", "label": "Custom timeout and poll values are stored.", "file_type": "rationale", "source_file": "tests/test_locks.py", "source_location": "L166"}, {"id": "tests_test_locks_rationale_175", "label": "Tests for hero.core.exchange.", "file_type": "rationale", "source_file": "tests/test_locks.py", "source_location": "L175"}, {"id": "tests_test_locks_rationale_179", "label": "Redirect EXCHANGE_DIR to a temp directory.", "file_type": "rationale", "source_file": "tests/test_locks.py", "source_location": "L179"}, {"id": "tests_test_locks_rationale_188", "label": "Messages posted can be read back in order.", "file_type": "rationale", "source_file": "tests/test_locks.py", "source_location": "L188"}, {"id": "tests_test_locks_rationale_203", "label": "post_message returns the file path it wrote to.", "file_type": "rationale", "source_file": "tests/test_locks.py", "source_location": "L203"}, {"id": "tests_test_locks_rationale_216", "label": "read_messages returns empty list for non-existent channel.", "file_type": "rationale", "source_file": "tests/test_locks.py", "source_location": "L216"}, {"id": "tests_test_locks_rationale_223", "label": "read_messages returns empty list when channel dir exists but is empty.", "file_type": "rationale", "source_file": "tests/test_locks.py", "source_location": "L223"}, {"id": "tests_test_locks_rationale_231", "label": "read_state returns state dict or None.", "file_type": "rationale", "source_file": "tests/test_locks.py", "source_location": "L231"}, {"id": "tests_test_locks_rationale_244", "label": "write_state overwrites the previous state.", "file_type": "rationale", "source_file": "tests/test_locks.py", "source_location": "L244"}, {"id": "tests_test_locks_rationale_256", "label": "ensure_channel creates the messages directory.", "file_type": "rationale", "source_file": "tests/test_locks.py", "source_location": "L256"}, {"id": "tests_test_locks_rationale_265", "label": "Sequence numbers increment correctly per soldier.", "file_type": "rationale", "source_file": "tests/test_locks.py", "source_location": "L265"}, {"id": "tests_test_locks_rationale_279", "label": "Full round-trip: post complex message \u2192 read it back intact.", "file_type": "rationale", "source_file": "tests/test_locks.py", "source_location": "L279"}, {"id": "tests_test_locks_rationale_298", "label": "Verify that locks and exchange work together in realistic scenarios.", "file_type": "rationale", "source_file": "tests/test_locks.py", "source_location": "L298"}, {"id": "tests_test_locks_rationale_302", "label": "Isolate both lock and exchange directories.", "file_type": "rationale", "source_file": "tests/test_locks.py", "source_location": "L302"}, {"id": "tests_test_locks_rationale_313", "label": "write_state uses FileLock to serialise concurrent writes.", "file_type": "rationale", "source_file": "tests/test_locks.py", "source_location": "L313"}, {"id": "tests_test_locks_rationale_329", "label": "Multiple soldiers can post to the same channel without contention.", "file_type": "rationale", "source_file": "tests/test_locks.py", "source_location": "L329"}], "edges": [{"source": "home_max_development_hero_tests_test_locks_py", "target": "json", "relation": "imports", "context": "import", "confidence": "EXTRACTED", "source_file": "tests/test_locks.py", "source_location": "L5", "weight": 1.0}, {"source": "home_max_development_hero_tests_test_locks_py", "target": "multiprocessing", "relation": "imports", "context": "import", "confidence": "EXTRACTED", "source_file": "tests/test_locks.py", "source_location": "L6", "weight": 1.0}, {"source": "home_max_development_hero_tests_test_locks_py", "target": "os", "relation": "imports", "context": "import", "confidence": "EXTRACTED", "source_file": "tests/test_locks.py", "source_location": "L7", "weight": 1.0}, {"source": "home_max_development_hero_tests_test_locks_py", "target": "tempfile", "relation": "imports", "context": "import", "confidence": "EXTRACTED", "source_file": "tests/test_locks.py", "source_location": "L8", "weight": 1.0}, {"source": "home_max_development_hero_tests_test_locks_py", "target": "time", "relation": "imports", "context": "import", "confidence": "EXTRACTED", "source_file": "tests/test_locks.py", "source_location": "L9", "weight": 1.0}, {"source": "home_max_development_hero_tests_test_locks_py", "target": "pathlib", "relation": "imports_from", "context": "import", "confidence": "EXTRACTED", "source_file": "tests/test_locks.py", "source_location": "L10", "weight": 1.0}, {"source": "home_max_development_hero_tests_test_locks_py", "target": "pytest", "relation": "imports", "context": "import", "confidence": "EXTRACTED", "source_file": "tests/test_locks.py", "source_location": "L12", "weight": 1.0}, {"source": "home_max_development_hero_tests_test_locks_py", "target": "hero_core_locks", "relation": "imports_from", "context": "import", "confidence": "EXTRACTED", "source_file": "tests/test_locks.py", "source_location": "L14", "weight": 1.0}, {"source": "home_max_development_hero_tests_test_locks_py", "target": "tests_test_locks_isolate_lock_dir", "relation": "contains", "confidence": "EXTRACTED", "source_file": "tests/test_locks.py", "source_location": "L20", "weight": 1.0}, {"source": "tests_test_locks_isolate_lock_dir", "target": "monkeypatch", "relation": "references", "context": "parameter_type", "confidence": "EXTRACTED", "source_file": "tests/test_locks.py", "source_location": "L20", "weight": 1.0}, {"source": "tests_test_locks_isolate_lock_dir", "target": "path", "relation": "references", "context": "return_type", "confidence": "EXTRACTED", "source_file": "tests/test_locks.py", "source_location": "L20", "weight": 1.0}, {"source": "home_max_development_hero_tests_test_locks_py", "target": "tests_test_locks_testfilelock", "relation": "contains", "confidence": "EXTRACTED", "source_file": "tests/test_locks.py", "source_location": "L29", "weight": 1.0}, {"source": "tests_test_locks_testfilelock", "target": "tests_test_locks_testfilelock_test_acquire_and_release", "relation": "method", "confidence": "EXTRACTED", "source_file": "tests/test_locks.py", "source_location": "L32", "weight": 1.0}, {"source": "tests_test_locks_testfilelock", "target": "tests_test_locks_testfilelock_test_lock_path_created", "relation": "method", "confidence": "EXTRACTED", "source_file": "tests/test_locks.py", "source_location": "L47", "weight": 1.0}, {"source": "tests_test_locks_testfilelock", "target": "tests_test_locks_testfilelock_test_different_resources_dont_block", "relation": "method", "confidence": "EXTRACTED", "source_file": "tests/test_locks.py", "source_location": "L55", "weight": 1.0}, {"source": "tests_test_locks_testfilelock", "target": "tests_test_locks_testfilelock_test_timeout_when_contended", "relation": "method", "confidence": "EXTRACTED", "source_file": "tests/test_locks.py", "source_location": "L66", "weight": 1.0}, {"source": "tests_test_locks_testfilelock", "target": "tests_test_locks_testfilelock_test_reentrant_same_process", "relation": "method", "confidence": "EXTRACTED", "source_file": "tests/test_locks.py", "source_location": "L98", "weight": 1.0}, {"source": "tests_test_locks_testfilelock", "target": "tests_test_locks_testfilelock_test_lock_exclusive_across_threads", "relation": "method", "confidence": "EXTRACTED", "source_file": "tests/test_locks.py", "source_location": "L108", "weight": 1.0}, {"source": "tests_test_locks_testfilelock", "target": "tests_test_locks_testfilelock_test_cleanup_on_file_not_exists", "relation": "method", "confidence": "EXTRACTED", "source_file": "tests/test_locks.py", "source_location": "L143", "weight": 1.0}, {"source": "tests_test_locks_testfilelock", "target": "tests_test_locks_testfilelock_test_default_timeout", "relation": "method", "confidence": "EXTRACTED", "source_file": "tests/test_locks.py", "source_location": "L159", "weight": 1.0}, {"source": "tests_test_locks_testfilelock", "target": "tests_test_locks_testfilelock_test_custom_timeout_and_poll", "relation": "method", "confidence": "EXTRACTED", "source_file": "tests/test_locks.py", "source_location": "L165", "weight": 1.0}, {"source": "home_max_development_hero_tests_test_locks_py", "target": "tests_test_locks_testexchange", "relation": "contains", "confidence": "EXTRACTED", "source_file": "tests/test_locks.py", "source_location": "L174", "weight": 1.0}, {"source": "tests_test_locks_testexchange", "target": "tests_test_locks_testexchange_isolate_exchange_dir", "relation": "method", "confidence": "EXTRACTED", "source_file": "tests/test_locks.py", "source_location": "L178", "weight": 1.0}, {"source": "tests_test_locks_testexchange_isolate_exchange_dir", "target": "monkeypatch", "relation": "references", "context": "parameter_type", "confidence": "EXTRACTED", "source_file": "tests/test_locks.py", "source_location": "L178", "weight": 1.0}, {"source": "tests_test_locks_testexchange_isolate_exchange_dir", "target": "path", "relation": "references", "context": "return_type", "confidence": "EXTRACTED", "source_file": "tests/test_locks.py", "source_location": "L178", "weight": 1.0}, {"source": "tests_test_locks_testexchange", "target": "tests_test_locks_testexchange_test_post_and_read_messages", "relation": "method", "confidence": "EXTRACTED", "source_file": "tests/test_locks.py", "source_location": "L187", "weight": 1.0}, {"source": "tests_test_locks_testexchange", "target": "tests_test_locks_testexchange_test_post_message_returns_path", "relation": "method", "confidence": "EXTRACTED", "source_file": "tests/test_locks.py", "source_location": "L202", "weight": 1.0}, {"source": "tests_test_locks_testexchange", "target": "tests_test_locks_testexchange_test_read_empty_channel", "relation": "method", "confidence": "EXTRACTED", "source_file": "tests/test_locks.py", "source_location": "L215", "weight": 1.0}, {"source": "tests_test_locks_testexchange", "target": "tests_test_locks_testexchange_test_read_empty_messages_dir", "relation": "method", "confidence": "EXTRACTED", "source_file": "tests/test_locks.py", "source_location": "L222", "weight": 1.0}, {"source": "tests_test_locks_testexchange", "target": "tests_test_locks_testexchange_test_read_state", "relation": "method", "confidence": "EXTRACTED", "source_file": "tests/test_locks.py", "source_location": "L230", "weight": 1.0}, {"source": "tests_test_locks_testexchange", "target": "tests_test_locks_testexchange_test_write_state_overwrites", "relation": "method", "confidence": "EXTRACTED", "source_file": "tests/test_locks.py", "source_location": "L243", "weight": 1.0}, {"source": "tests_test_locks_testexchange", "target": "tests_test_locks_testexchange_test_ensure_channel", "relation": "method", "confidence": "EXTRACTED", "source_file": "tests/test_locks.py", "source_location": "L255", "weight": 1.0}, {"source": "tests_test_locks_testexchange", "target": "tests_test_locks_testexchange_test_post_message_sequence_ordering", "relation": "method", "confidence": "EXTRACTED", "source_file": "tests/test_locks.py", "source_location": "L264", "weight": 1.0}, {"source": "tests_test_locks_testexchange", "target": "tests_test_locks_testexchange_test_message_round_trip", "relation": "method", "confidence": "EXTRACTED", "source_file": "tests/test_locks.py", "source_location": "L278", "weight": 1.0}, {"source": "home_max_development_hero_tests_test_locks_py", "target": "tests_test_locks_testlockandexchange", "relation": "contains", "confidence": "EXTRACTED", "source_file": "tests/test_locks.py", "source_location": "L297", "weight": 1.0}, {"source": "tests_test_locks_testlockandexchange", "target": "tests_test_locks_testlockandexchange_isolate", "relation": "method", "confidence": "EXTRACTED", "source_file": "tests/test_locks.py", "source_location": "L301", "weight": 1.0}, {"source": "tests_test_locks_testlockandexchange_isolate", "target": "monkeypatch", "relation": "references", "context": "parameter_type", "confidence": "EXTRACTED", "source_file": "tests/test_locks.py", "source_location": "L301", "weight": 1.0}, {"source": "tests_test_locks_testlockandexchange", "target": "tests_test_locks_testlockandexchange_test_write_state_under_lock", "relation": "method", "confidence": "EXTRACTED", "source_file": "tests/test_locks.py", "source_location": "L312", "weight": 1.0}, {"source": "tests_test_locks_testlockandexchange", "target": "tests_test_locks_testlockandexchange_test_same_channel_multiple_soldiers", "relation": "method", "confidence": "EXTRACTED", "source_file": "tests/test_locks.py", "source_location": "L328", "weight": 1.0}, {"source": "tests_test_locks_isolate_lock_dir", "target": "path", "relation": "calls", "context": "call", "confidence": "EXTRACTED", "source_file": "tests/test_locks.py", "source_location": "L23", "weight": 1.0}, {"source": "tests_test_locks_testfilelock_test_timeout_when_contended", "target": "path", "relation": "calls", "context": "call", "confidence": "EXTRACTED", "source_file": "tests/test_locks.py", "source_location": "L90", "weight": 1.0}, {"source": "tests_test_locks_testexchange_isolate_exchange_dir", "target": "path", "relation": "calls", "context": "call", "confidence": "EXTRACTED", "source_file": "tests/test_locks.py", "source_location": "L183", "weight": 1.0}, {"source": "tests_test_locks_testlockandexchange_isolate", "target": "path", "relation": "calls", "context": "call", "confidence": "EXTRACTED", "source_file": "tests/test_locks.py", "source_location": "L308", "weight": 1.0}, {"source": "tests_test_locks_rationale_1", "target": "home_max_development_hero_tests_test_locks_py", "relation": "rationale_for", "confidence": "EXTRACTED", "source_file": "tests/test_locks.py", "source_location": "L1", "weight": 1.0}, {"source": "tests_test_locks_rationale_21", "target": "tests_test_locks_isolate_lock_dir", "relation": "rationale_for", "confidence": "EXTRACTED", "source_file": "tests/test_locks.py", "source_location": "L21", "weight": 1.0}, {"source": "tests_test_locks_rationale_30", "target": "tests_test_locks_testfilelock", "relation": "rationale_for", "confidence": "EXTRACTED", "source_file": "tests/test_locks.py", "source_location": "L30", "weight": 1.0}, {"source": "tests_test_locks_rationale_33", "target": "tests_test_locks_testfilelock_test_acquire_and_release", "relation": "rationale_for", "confidence": "EXTRACTED", "source_file": "tests/test_locks.py", "source_location": "L33", "weight": 1.0}, {"source": "tests_test_locks_rationale_48", "target": "tests_test_locks_testfilelock_test_lock_path_created", "relation": "rationale_for", "confidence": "EXTRACTED", "source_file": "tests/test_locks.py", "source_location": "L48", "weight": 1.0}, {"source": "tests_test_locks_rationale_56", "target": "tests_test_locks_testfilelock_test_different_resources_dont_block", "relation": "rationale_for", "confidence": "EXTRACTED", "source_file": "tests/test_locks.py", "source_location": "L56", "weight": 1.0}, {"source": "tests_test_locks_rationale_67", "target": "tests_test_locks_testfilelock_test_timeout_when_contended", "relation": "rationale_for", "confidence": "EXTRACTED", "source_file": "tests/test_locks.py", "source_location": "L67", "weight": 1.0}, {"source": "tests_test_locks_rationale_99", "target": "tests_test_locks_testfilelock_test_reentrant_same_process", "relation": "rationale_for", "confidence": "EXTRACTED", "source_file": "tests/test_locks.py", "source_location": "L99", "weight": 1.0}, {"source": "tests_test_locks_rationale_109", "target": "tests_test_locks_testfilelock_test_lock_exclusive_across_threads", "relation": "rationale_for", "confidence": "EXTRACTED", "source_file": "tests/test_locks.py", "source_location": "L109", "weight": 1.0}, {"source": "tests_test_locks_rationale_144", "target": "tests_test_locks_testfilelock_test_cleanup_on_file_not_exists", "relation": "rationale_for", "confidence": "EXTRACTED", "source_file": "tests/test_locks.py", "source_location": "L144", "weight": 1.0}, {"source": "tests_test_locks_rationale_160", "target": "tests_test_locks_testfilelock_test_default_timeout", "relation": "rationale_for", "confidence": "EXTRACTED", "source_file": "tests/test_locks.py", "source_location": "L160", "weight": 1.0}, {"source": "tests_test_locks_rationale_166", "target": "tests_test_locks_testfilelock_test_custom_timeout_and_poll", "relation": "rationale_for", "confidence": "EXTRACTED", "source_file": "tests/test_locks.py", "source_location": "L166", "weight": 1.0}, {"source": "tests_test_locks_rationale_175", "target": "tests_test_locks_testexchange", "relation": "rationale_for", "confidence": "EXTRACTED", "source_file": "tests/test_locks.py", "source_location": "L175", "weight": 1.0}, {"source": "tests_test_locks_rationale_179", "target": "tests_test_locks_testexchange_isolate_exchange_dir", "relation": "rationale_for", "confidence": "EXTRACTED", "source_file": "tests/test_locks.py", "source_location": "L179", "weight": 1.0}, {"source": "tests_test_locks_rationale_188", "target": "tests_test_locks_testexchange_test_post_and_read_messages", "relation": "rationale_for", "confidence": "EXTRACTED", "source_file": "tests/test_locks.py", "source_location": "L188", "weight": 1.0}, {"source": "tests_test_locks_rationale_203", "target": "tests_test_locks_testexchange_test_post_message_returns_path", "relation": "rationale_for", "confidence": "EXTRACTED", "source_file": "tests/test_locks.py", "source_location": "L203", "weight": 1.0}, {"source": "tests_test_locks_rationale_216", "target": "tests_test_locks_testexchange_test_read_empty_channel", "relation": "rationale_for", "confidence": "EXTRACTED", "source_file": "tests/test_locks.py", "source_location": "L216", "weight": 1.0}, {"source": "tests_test_locks_rationale_223", "target": "tests_test_locks_testexchange_test_read_empty_messages_dir", "relation": "rationale_for", "confidence": "EXTRACTED", "source_file": "tests/test_locks.py", "source_location": "L223", "weight": 1.0}, {"source": "tests_test_locks_rationale_231", "target": "tests_test_locks_testexchange_test_read_state", "relation": "rationale_for", "confidence": "EXTRACTED", "source_file": "tests/test_locks.py", "source_location": "L231", "weight": 1.0}, {"source": "tests_test_locks_rationale_244", "target": "tests_test_locks_testexchange_test_write_state_overwrites", "relation": "rationale_for", "confidence": "EXTRACTED", "source_file": "tests/test_locks.py", "source_location": "L244", "weight": 1.0}, {"source": "tests_test_locks_rationale_256", "target": "tests_test_locks_testexchange_test_ensure_channel", "relation": "rationale_for", "confidence": "EXTRACTED", "source_file": "tests/test_locks.py", "source_location": "L256", "weight": 1.0}, {"source": "tests_test_locks_rationale_265", "target": "tests_test_locks_testexchange_test_post_message_sequence_ordering", "relation": "rationale_for", "confidence": "EXTRACTED", "source_file": "tests/test_locks.py", "source_location": "L265", "weight": 1.0}, {"source": "tests_test_locks_rationale_279", "target": "tests_test_locks_testexchange_test_message_round_trip", "relation": "rationale_for", "confidence": "EXTRACTED", "source_file": "tests/test_locks.py", "source_location": "L279", "weight": 1.0}, {"source": "tests_test_locks_rationale_298", "target": "tests_test_locks_testlockandexchange", "relation": "rationale_for", "confidence": "EXTRACTED", "source_file": "tests/test_locks.py", "source_location": "L298", "weight": 1.0}, {"source": "tests_test_locks_rationale_302", "target": "tests_test_locks_testlockandexchange_isolate", "relation": "rationale_for", "confidence": "EXTRACTED", "source_file": "tests/test_locks.py", "source_location": "L302", "weight": 1.0}, {"source": "tests_test_locks_rationale_313", "target": "tests_test_locks_testlockandexchange_test_write_state_under_lock", "relation": "rationale_for", "confidence": "EXTRACTED", "source_file": "tests/test_locks.py", "source_location": "L313", "weight": 1.0}, {"source": "tests_test_locks_rationale_329", "target": "tests_test_locks_testlockandexchange_test_same_channel_multiple_soldiers", "relation": "rationale_for", "confidence": "EXTRACTED", "source_file": "tests/test_locks.py", "source_location": "L329", "weight": 1.0}], "raw_calls": [{"caller_nid": "tests_test_locks_isolate_lock_dir", "callee": "mkdtemp", "is_member_call": true, "source_file": "/home/max/Development/HERO/tests/test_locks.py", "source_location": "L22"}, {"caller_nid": "tests_test_locks_testfilelock_test_acquire_and_release", "callee": "FileLock", "is_member_call": false, "source_file": "/home/max/Development/HERO/tests/test_locks.py", "source_location": "L34"}, {"caller_nid": "tests_test_locks_testfilelock_test_acquire_and_release", "callee": "exists", "is_member_call": true, "source_file": "/home/max/Development/HERO/tests/test_locks.py", "source_location": "L40"}, {"caller_nid": "tests_test_locks_testfilelock_test_acquire_and_release", "callee": "exists", "is_member_call": true, "source_file": "/home/max/Development/HERO/tests/test_locks.py", "source_location": "L42"}, {"caller_nid": "tests_test_locks_testfilelock_test_lock_path_created", "callee": "FileLock", "is_member_call": false, "source_file": "/home/max/Development/HERO/tests/test_locks.py", "source_location": "L49"}, {"caller_nid": "tests_test_locks_testfilelock_test_lock_path_created", "callee": "exists", "is_member_call": true, "source_file": "/home/max/Development/HERO/tests/test_locks.py", "source_location": "L51"}, {"caller_nid": "tests_test_locks_testfilelock_test_lock_path_created", "callee": "endswith", "is_member_call": true, "source_file": "/home/max/Development/HERO/tests/test_locks.py", "source_location": "L53"}, {"caller_nid": "tests_test_locks_testfilelock_test_different_resources_dont_block", "callee": "FileLock", "is_member_call": false, "source_file": "/home/max/Development/HERO/tests/test_locks.py", "source_location": "L57"}, {"caller_nid": "tests_test_locks_testfilelock_test_different_resources_dont_block", "callee": "FileLock", "is_member_call": false, "source_file": "/home/max/Development/HERO/tests/test_locks.py", "source_location": "L58"}, {"caller_nid": "tests_test_locks_testfilelock_test_timeout_when_contended", "callee": "mkdtemp", "is_member_call": true, "source_file": "/home/max/Development/HERO/tests/test_locks.py", "source_location": "L81"}, {"caller_nid": "tests_test_locks_testfilelock_test_timeout_when_contended", "callee": "Event", "is_member_call": true, "source_file": "/home/max/Development/HERO/tests/test_locks.py", "source_location": "L82"}, {"caller_nid": "tests_test_locks_testfilelock_test_timeout_when_contended", "callee": "Process", "is_member_call": true, "source_file": "/home/max/Development/HERO/tests/test_locks.py", "source_location": "L83"}, {"caller_nid": "tests_test_locks_testfilelock_test_timeout_when_contended", "callee": "start", "is_member_call": true, "source_file": "/home/max/Development/HERO/tests/test_locks.py", "source_location": "L84"}, {"caller_nid": "tests_test_locks_testfilelock_test_timeout_when_contended", "callee": "wait", "is_member_call": true, "source_file": "/home/max/Development/HERO/tests/test_locks.py", "source_location": "L85"}, {"caller_nid": "tests_test_locks_testfilelock_test_timeout_when_contended", "callee": "FileLock", "is_member_call": false, "source_file": "/home/max/Development/HERO/tests/test_locks.py", "source_location": "L91"}, {"caller_nid": "tests_test_locks_testfilelock_test_timeout_when_contended", "callee": "raises", "is_member_call": true, "source_file": "/home/max/Development/HERO/tests/test_locks.py", "source_location": "L92"}, {"caller_nid": "tests_test_locks_testfilelock_test_timeout_when_contended", "callee": "join", "is_member_call": true, "source_file": "/home/max/Development/HERO/tests/test_locks.py", "source_location": "L96"}, {"caller_nid": "tests_test_locks_testfilelock_test_reentrant_same_process", "callee": "FileLock", "is_member_call": false, "source_file": "/home/max/Development/HERO/tests/test_locks.py", "source_location": "L100"}, {"caller_nid": "tests_test_locks_testfilelock_test_lock_exclusive_across_threads", "callee": "Event", "is_member_call": true, "source_file": "/home/max/Development/HERO/tests/test_locks.py", "source_location": "L112"}, {"caller_nid": "tests_test_locks_testfilelock_test_lock_exclusive_across_threads", "callee": "Event", "is_member_call": true, "source_file": "/home/max/Development/HERO/tests/test_locks.py", "source_location": "L113"}, {"caller_nid": "tests_test_locks_testfilelock_test_lock_exclusive_across_threads", "callee": "Thread", "is_member_call": true, "source_file": "/home/max/Development/HERO/tests/test_locks.py", "source_location": "L133"}, {"caller_nid": "tests_test_locks_testfilelock_test_lock_exclusive_across_threads", "callee": "Thread", "is_member_call": true, "source_file": "/home/max/Development/HERO/tests/test_locks.py", "source_location": "L134"}, {"caller_nid": "tests_test_locks_testfilelock_test_lock_exclusive_across_threads", "callee": "start", "is_member_call": true, "source_file": "/home/max/Development/HERO/tests/test_locks.py", "source_location": "L135"}, {"caller_nid": "tests_test_locks_testfilelock_test_lock_exclusive_across_threads", "callee": "wait", "is_member_call": true, "source_file": "/home/max/Development/HERO/tests/test_locks.py", "source_location": "L136"}, {"caller_nid": "tests_test_locks_testfilelock_test_lock_exclusive_across_threads", "callee": "start", "is_member_call": true, "source_file": "/home/max/Development/HERO/tests/test_locks.py", "source_location": "L137"}, {"caller_nid": "tests_test_locks_testfilelock_test_lock_exclusive_across_threads", "callee": "join", "is_member_call": true, "source_file": "/home/max/Development/HERO/tests/test_locks.py", "source_location": "L138"}, {"caller_nid": "tests_test_locks_testfilelock_test_lock_exclusive_across_threads", "callee": "join", "is_member_call": true, "source_file": "/home/max/Development/HERO/tests/test_locks.py", "source_location": "L139"}, {"caller_nid": "tests_test_locks_testfilelock_test_cleanup_on_file_not_exists", "callee": "FileLock", "is_member_call": false, "source_file": "/home/max/Development/HERO/tests/test_locks.py", "source_location": "L145"}, {"caller_nid": "tests_test_locks_testfilelock_test_cleanup_on_file_not_exists", "callee": "unlink", "is_member_call": true, "source_file": "/home/max/Development/HERO/tests/test_locks.py", "source_location": "L151"}, {"caller_nid": "tests_test_locks_testfilelock_test_default_timeout", "callee": "FileLock", "is_member_call": false, "source_file": "/home/max/Development/HERO/tests/test_locks.py", "source_location": "L161"}, {"caller_nid": "tests_test_locks_testfilelock_test_custom_timeout_and_poll", "callee": "FileLock", "is_member_call": false, "source_file": "/home/max/Development/HERO/tests/test_locks.py", "source_location": "L167"}, {"caller_nid": "tests_test_locks_testexchange_isolate_exchange_dir", "callee": "mkdtemp", "is_member_call": true, "source_file": "/home/max/Development/HERO/tests/test_locks.py", "source_location": "L182"}, {"caller_nid": "tests_test_locks_testexchange_test_post_and_read_messages", "callee": "post_message", "is_member_call": false, "source_file": "/home/max/Development/HERO/tests/test_locks.py", "source_location": "L191"}, {"caller_nid": "tests_test_locks_testexchange_test_post_and_read_messages", "callee": "post_message", "is_member_call": false, "source_file": "/home/max/Development/HERO/tests/test_locks.py", "source_location": "L192"}, {"caller_nid": "tests_test_locks_testexchange_test_post_and_read_messages", "callee": "post_message", "is_member_call": false, "source_file": "/home/max/Development/HERO/tests/test_locks.py", "source_location": "L193"}, {"caller_nid": "tests_test_locks_testexchange_test_post_and_read_messages", "callee": "read_messages", "is_member_call": false, "source_file": "/home/max/Development/HERO/tests/test_locks.py", "source_location": "L195"}, {"caller_nid": "tests_test_locks_testexchange_test_post_message_returns_path", "callee": "post_message", "is_member_call": false, "source_file": "/home/max/Development/HERO/tests/test_locks.py", "source_location": "L206"}, {"caller_nid": "tests_test_locks_testexchange_test_post_message_returns_path", "callee": "exists", "is_member_call": true, "source_file": "/home/max/Development/HERO/tests/test_locks.py", "source_location": "L207"}, {"caller_nid": "tests_test_locks_testexchange_test_post_message_returns_path", "callee": "loads", "is_member_call": true, "source_file": "/home/max/Development/HERO/tests/test_locks.py", "source_location": "L212"}, {"caller_nid": "tests_test_locks_testexchange_test_post_message_returns_path", "callee": "read_text", "is_member_call": true, "source_file": "/home/max/Development/HERO/tests/test_locks.py", "source_location": "L212"}, {"caller_nid": "tests_test_locks_testexchange_test_read_empty_channel", "callee": "read_messages", "is_member_call": false, "source_file": "/home/max/Development/HERO/tests/test_locks.py", "source_location": "L219"}, {"caller_nid": "tests_test_locks_testexchange_test_read_empty_messages_dir", "callee": "ensure_channel", "is_member_call": false, "source_file": "/home/max/Development/HERO/tests/test_locks.py", "source_location": "L226"}, {"caller_nid": "tests_test_locks_testexchange_test_read_empty_messages_dir", "callee": "read_messages", "is_member_call": false, "source_file": "/home/max/Development/HERO/tests/test_locks.py", "source_location": "L227"}, {"caller_nid": "tests_test_locks_testexchange_test_read_state", "callee": "read_state", "is_member_call": false, "source_file": "/home/max/Development/HERO/tests/test_locks.py", "source_location": "L235"}, {"caller_nid": "tests_test_locks_testexchange_test_read_state", "callee": "write_state", "is_member_call": false, "source_file": "/home/max/Development/HERO/tests/test_locks.py", "source_location": "L237"}, {"caller_nid": "tests_test_locks_testexchange_test_read_state", "callee": "read_state", "is_member_call": false, "source_file": "/home/max/Development/HERO/tests/test_locks.py", "source_location": "L238"}, {"caller_nid": "tests_test_locks_testexchange_test_write_state_overwrites", "callee": "write_state", "is_member_call": false, "source_file": "/home/max/Development/HERO/tests/test_locks.py", "source_location": "L247"}, {"caller_nid": "tests_test_locks_testexchange_test_write_state_overwrites", "callee": "write_state", "is_member_call": false, "source_file": "/home/max/Development/HERO/tests/test_locks.py", "source_location": "L248"}, {"caller_nid": "tests_test_locks_testexchange_test_write_state_overwrites", "callee": "read_state", "is_member_call": false, "source_file": "/home/max/Development/HERO/tests/test_locks.py", "source_location": "L250"}, {"caller_nid": "tests_test_locks_testexchange_test_ensure_channel", "callee": "ensure_channel", "is_member_call": false, "source_file": "/home/max/Development/HERO/tests/test_locks.py", "source_location": "L259"}, {"caller_nid": "tests_test_locks_testexchange_test_ensure_channel", "callee": "exists", "is_member_call": true, "source_file": "/home/max/Development/HERO/tests/test_locks.py", "source_location": "L260"}, {"caller_nid": "tests_test_locks_testexchange_test_ensure_channel", "callee": "is_dir", "is_member_call": true, "source_file": "/home/max/Development/HERO/tests/test_locks.py", "source_location": "L261"}, {"caller_nid": "tests_test_locks_testexchange_test_post_message_sequence_ordering", "callee": "post_message", "is_member_call": false, "source_file": "/home/max/Development/HERO/tests/test_locks.py", "source_location": "L268"}, {"caller_nid": "tests_test_locks_testexchange_test_post_message_sequence_ordering", "callee": "post_message", "is_member_call": false, "source_file": "/home/max/Development/HERO/tests/test_locks.py", "source_location": "L269"}, {"caller_nid": "tests_test_locks_testexchange_test_post_message_sequence_ordering", "callee": "post_message", "is_member_call": false, "source_file": "/home/max/Development/HERO/tests/test_locks.py", "source_location": "L270"}, {"caller_nid": "tests_test_locks_testexchange_test_post_message_sequence_ordering", "callee": "post_message", "is_member_call": false, "source_file": "/home/max/Development/HERO/tests/test_locks.py", "source_location": "L271"}, {"caller_nid": "tests_test_locks_testexchange_test_post_message_sequence_ordering", "callee": "read_messages", "is_member_call": false, "source_file": "/home/max/Development/HERO/tests/test_locks.py", "source_location": "L273"}, {"caller_nid": "tests_test_locks_testexchange_test_message_round_trip", "callee": "post_message", "is_member_call": false, "source_file": "/home/max/Development/HERO/tests/test_locks.py", "source_location": "L289"}, {"caller_nid": "tests_test_locks_testexchange_test_message_round_trip", "callee": "read_messages", "is_member_call": false, "source_file": "/home/max/Development/HERO/tests/test_locks.py", "source_location": "L290"}, {"caller_nid": "tests_test_locks_testlockandexchange_isolate", "callee": "mkdtemp", "is_member_call": true, "source_file": "/home/max/Development/HERO/tests/test_locks.py", "source_location": "L306"}, {"caller_nid": "tests_test_locks_testlockandexchange_isolate", "callee": "mkdtemp", "is_member_call": true, "source_file": "/home/max/Development/HERO/tests/test_locks.py", "source_location": "L307"}, {"caller_nid": "tests_test_locks_testlockandexchange_test_write_state_under_lock", "callee": "write_state", "is_member_call": false, "source_file": "/home/max/Development/HERO/tests/test_locks.py", "source_location": "L318"}, {"caller_nid": "tests_test_locks_testlockandexchange_test_write_state_under_lock", "callee": "read_state", "is_member_call": false, "source_file": "/home/max/Development/HERO/tests/test_locks.py", "source_location": "L319"}, {"caller_nid": "tests_test_locks_testlockandexchange_test_write_state_under_lock", "callee": "write_state", "is_member_call": false, "source_file": "/home/max/Development/HERO/tests/test_locks.py", "source_location": "L324"}, {"caller_nid": "tests_test_locks_testlockandexchange_test_write_state_under_lock", "callee": "read_state", "is_member_call": false, "source_file": "/home/max/Development/HERO/tests/test_locks.py", "source_location": "L325"}, {"caller_nid": "tests_test_locks_testlockandexchange_test_same_channel_multiple_soldiers", "callee": "post_message", "is_member_call": false, "source_file": "/home/max/Development/HERO/tests/test_locks.py", "source_location": "L336"}, {"caller_nid": "tests_test_locks_testlockandexchange_test_same_channel_multiple_soldiers", "callee": "read_messages", "is_member_call": false, "source_file": "/home/max/Development/HERO/tests/test_locks.py", "source_location": "L338"}]}